Metadata-Version: 2.4
Name: sakhilabs
Version: 0.0.1
Summary: Sakhi - Tools for building and using AI models for Indic languages
Author-email: Abhinav Reddy Mandli <raabhinav65@gmail.com>
License: MIT
Keywords: sakhi,indicAI,AI Library Indic Languages
Requires-Python: >=3.9
Requires-Dist: torch==2.7.0
Requires-Dist: datasets==3.6.0
Requires-Dist: transformers==4.52.3
Requires-Dist: datasketch==1.6.5
Requires-Dist: wandb==0.20.1
